osdk_manager/__about__.py
osdk_manager/__init__.py
osdk_manager/__main__.py
osdk_manager/exceptions.py
osdk_manager/util.py
osdk_manager/cli/__init__.py
osdk_manager/cli/opm.py
osdk_manager/cli/osdk.py
osdk_manager/cli/util.py
osdk_manager/operator/__init__.py
osdk_manager/operator/operator.py
osdk_manager/opm/__init__.py
osdk_manager/opm/update.py
osdk_manager/osdk/__init__.py
osdk_manager/osdk/update.py
osdk_manager-0.3.1.dist-info/LICENSE
osdk_manager-0.3.1.dist-info/METADATA
osdk_manager-0.3.1.dist-info/WHEEL
osdk_manager-0.3.1.dist-info/entry_points.txt
osdk_manager-0.3.1.dist-info/top_level.txt
osdk_manager-0.3.1.dist-info/RECORD
